{
  "title": "荆钗记",
  "type": "京剧剧本",
  "author": "新中国",
  "year": 1900,
  "url": "",
  "image": "",
  "num_chapters": 9,
  "num_scenes": 21,
  "num_characters": 17,
  "num_locations": 3,
  "source_file": "03077002_荆钗记.json",
  "source_folder": "03000000",
  "plot_summary": "钱载和有女钱玉莲，拟许旧友王氏之子王十朋，继室孙氏则欲嫁与己侄孙汝权，互争不决，因取两家聘物使\n钱玉莲自择。钱玉莲选王十朋所送荆钗，遂嫁王十朋。王十朋赴考得中，因未允秦桧招赘，被谪潮州佥判；\n孙汝权假造王十朋家书，言王十朋已在相府招亲，并改钱玉莲为妾。孙氏因逼钱玉莲改嫁孙汝权。钱玉莲投\n江，为福建安抚使邓杰侯所救。王十朋遣人接母至潮州，闻钱玉莲噩耗，哀痛几绝，拟寻孙汝权辩理，而孙\n汝权亦因钱玉莲死亦自投江。时邓杰侯携夫人出巡潮州，伪称有女，强婚王十朋，更索荆钗为聘。洞房之夕，\n真相始明。",
  "performance_notes": "",
  "chapters": [
    {
      "chapter": "第1章",
      "numScenes": 3,
      "numLines": 104,
      "summary": "第一场；第二场；第三场",
      "conflict": 0.611,
      "importance": 1.0,
      "locations": {
        "温州城内双门巷": 3
      },
      "characters": {
        "王十朋": 1,
        "孙氏": 1,
        "李成": 1,
        "孙汝权": 1,
        "钱载和": 1,
        "王母": 1
      },
      "links": [
        {
          "source": "李成",
          "target": "钱载和",
          "value": 1
        },
        {
          "source": "孙氏",
          "target": "钱载和",
          "value": 1
        },
        {
          "source": "孙汝权",
          "target": "钱载和",
          "value": 1
        },
        {
          "source": "王十朋",
          "target": "钱载和",
          "value": 2
        },
        {
          "source": "孙氏",
          "target": "李成",
          "value": 1
        },
        {
          "source": "孙汝权",
          "target": "李成",
          "value": 1
        },
        {
          "source": "李成",
          "target": "王十朋",
          "value": 1
        },
        {
          "source": "孙氏",
          "target": "孙汝权",
          "value": 1
        },
        {
          "source": "孙氏",
          "target": "王十朋",
          "value": 1
        },
        {
          "source": "孙汝权",
          "target": "王十朋",
          "value": 1
        },
        {
          "source": "王十朋",
          "target": "王母",
          "value": 1
        },
        {
          "source": "王母",
          "target": "钱载和",
          "value": 1
        }
      ]
    },
    {
      "chapter": "第2章",
      "numScenes": 3,
      "numLines": 156,
      "summary": "第四场；第五场；第六场",
      "conflict": 0.524,
      "importance": 1.0,
      "locations": {
        "温州城内双门巷": 3
      },
      "characters": {
        "王十朋": 1,
        "孙氏": 1,
        "钱玉莲": 1,
        "钱载和": 1,
        "李成": 1,
        "孙汝权": 1,
        "王母": 1
      },
      "links": [
        {
          "source": "孙氏",
          "target": "钱载和",
          "value": 2
        },
        {
          "source": "王十朋",
          "target": "钱载和",
          "value": 2
        },
        {
          "source": "孙汝权",
          "target": "钱载和",
          "value": 1
        },
        {
          "source": "孙氏",
          "target": "王十朋",
          "value": 2
        },
        {
          "source": "孙氏",
          "target": "孙汝权",
          "value": 1
        },
        {
          "source": "孙汝权",
          "target": "王十朋",
          "value": 1
        },
        {
          "source": "钱玉莲",
          "target": "钱载和",
          "value": 1
        },
        {
          "source": "孙氏",
          "target": "钱玉莲",
          "value": 1
        },
        {
          "source": "李成",
          "target": "钱玉莲",
          "value": 1
        },
        {
          "source": "王十朋",
          "target": "钱玉莲",
          "value": 1
        },
        {
          "source": "李成",
          "target": "钱载和",
          "value": 1
        },
        {
          "source": "孙氏",
          "target": "李成",
          "value": 1
        },
        {
          "source": "李成",
          "target": "王十朋",
          "value": 2
        },
        {
          "source": "王十朋",
          "target": "王母",
          "value": 1
        },
        {
          "source": "李成",
          "target": "王母",
          "value": 1
        }
      ]
    },
    {
      "chapter": "第3章",
      "numScenes": 3,
      "numLines": 69,
      "summary": "第七场；第八场；第九场",
      "conflict": 0.787,
      "importance": 0.756,
      "locations": {
        "温州城内双门巷": 3
      },
      "characters": {
        "王十朋": 1,
        "孙氏": 1,
        "钱玉莲": 1,
        "李成": 1,
        "孙汝权": 1,
        "钱载和": 1,
        "王母": 1
      },
      "links": [
        {
          "source": "李成",
          "target": "钱载和",
          "value": 1
        },
        {
          "source": "钱玉莲",
          "target": "钱载和",
          "value": 1
        },
        {
          "source": "孙氏",
          "target": "钱载和",
          "value": 1
        },
        {
          "source": "李成",
          "target": "钱玉莲",
          "value": 1
        },
        {
          "source": "孙氏",
          "target": "李成",
          "value": 1
        },
        {
          "source": "孙氏",
          "target": "钱玉莲",
          "value": 1
        },
        {
          "source": "孙汝权",
          "target": "王十朋",
          "value": 1
        },
        {
          "source": "王母",
          "target": "钱玉莲",
          "value": 1
        },
        {
          "source": "王十朋",
          "target": "王母",
          "value": 1
        },
        {
          "source": "王十朋",
          "target": "钱玉莲",
          "value": 1
        }
      ]
    },
    {
      "chapter": "第4章",
      "numScenes": 3,
      "numLines": 133,
      "summary": "第十场；第十一场；第十二场",
      "conflict": 0.562,
      "importance": 1.0,
      "locations": {
        "温州城内双门巷": 3
      },
      "characters": {
        "王十朋": 1,
        "邓杰侯": 1,
        "孙氏": 1,
        "院子": 1,
        "四青袍": 1,
        "钱玉莲": 1,
        "钱载和": 1,
        "李成": 1,
        "孙汝权": 1,
        "王母": 1,
        "邓夫人": 1
      },
      "links": [
        {
          "source": "邓杰侯",
          "target": "院子",
          "value": 1
        },
        {
          "source": "邓夫人",
          "target": "邓杰侯",
          "value": 1
        },
        {
          "source": "邓夫人",
          "target": "院子",
          "value": 1
        },
        {
          "source": "四青袍",
          "target": "王十朋",
          "value": 1
        },
        {
          "source": "孙汝权",
          "target": "王十朋",
          "value": 2
        },
        {
          "source": "四青袍",
          "target": "孙汝权",
          "value": 1
        },
        {
          "source": "孙氏",
          "target": "钱载和",
          "value": 1
        },
        {
          "source": "孙汝权",
          "target": "钱载和",
          "value": 1
        },
        {
          "source": "李成",
          "target": "钱载和",
          "value": 1
        },
        {
          "source": "王母",
          "target": "钱载和",
          "value": 1
        },
        {
          "source": "钱玉莲",
          "target": "钱载和",
          "value": 1
        },
        {
          "source": "王十朋",
          "target": "钱载和",
          "value": 1
        },
        {
          "source": "孙氏",
          "target": "孙汝权",
          "value": 1
        },
        {
          "source": "孙氏",
          "target": "李成",
          "value": 1
        },
        {
          "source": "孙氏",
          "target": "王母",
          "value": 1
        },
        {
          "source": "孙氏",
          "target": "钱玉莲",
          "value": 1
        },
        {
          "source": "孙氏",
          "target": "王十朋",
          "value": 1
        },
        {
          "source": "孙汝权",
          "target": "李成",
          "value": 1
        },
        {
          "source": "孙汝权",
          "target": "王母",
          "value": 1
        },
        {
          "source": "孙汝权",
          "target": "钱玉莲",
          "value": 1
        },
        {
          "source": "李成",
          "target": "王母",
          "value": 1
        },
        {
          "source": "李成",
          "target": "钱玉莲",
          "value": 1
        },
        {
          "source": "李成",
          "target": "王十朋",
          "value": 1
        },
        {
          "source": "王母",
          "target": "钱玉莲",
          "value": 1
        },
        {
          "source": "王十朋",
          "target": "王母",
          "value": 1
        },
        {
          "source": "王十朋",
          "target": "钱玉莲",
          "value": 1
        }
      ]
    },
    {
      "chapter": "第5章",
      "numScenes": 3,
      "numLines": 94,
      "summary": "第十三场；第十四场；第十五场",
      "conflict": 0.073,
      "importance": 1.0,
      "locations": {
        "温州城内双门巷": 3
      },
      "characters": {
        "王十朋": 1,
        "旗牌": 1,
        "邓杰侯": 1,
        "孙氏": 1,
        "院子": 1,
        "钱玉莲": 1,
        "李成": 1,
        "孙汝权": 1,
        "钱载和": 1,
        "邓夫人": 1
      },
      "links": [
        {
          "source": "邓杰侯",
          "target": "钱玉莲",
          "value": 1
        },
        {
          "source": "邓夫人",
          "target": "钱玉莲",
          "value": 1
        },
        {
          "source": "王十朋",
          "target": "钱玉莲",
          "value": 1
        },
        {
          "source": "邓夫人",
          "target": "邓杰侯",
          "value": 1
        },
        {
          "source": "王十朋",
          "target": "邓杰侯",
          "value": 1
        },
        {
          "source": "王十朋",
          "target": "邓夫人",
          "value": 1
        },
        {
          "source": "孙汝权",
          "target": "李成",
          "value": 1
        },
        {
          "source": "孙汝权",
          "target": "钱载和",
          "value": 1
        },
        {
          "source": "孙氏",
          "target": "孙汝权",
          "value": 1
        },
        {
          "source": "李成",
          "target": "钱载和",
          "value": 1
        },
        {
          "source": "孙氏",
          "target": "李成",
          "value": 1
        },
        {
          "source": "孙氏",
          "target": "钱载和",
          "value": 1
        },
        {
          "source": "王十朋",
          "target": "院子",
          "value": 1
        },
        {
          "source": "旗牌",
          "target": "王十朋",
          "value": 1
        },
        {
          "source": "旗牌",
          "target": "院子",
          "value": 1
        }
      ]
    },
    {
      "chapter": "第6章",
      "numScenes": 3,
      "numLines": 145,
      "summary": "第十六场；第十七场；第十八场",
      "conflict": 0.707,
      "importance": 1.0,
      "locations": {
        "临任到闽城": 1,
        "温州城内双门巷": 2
      },
      "characters": {
        "王十朋": 1,
        "旗牌": 1,
        "邓杰侯": 1,
        "院子": 1,
        "钱玉莲": 1,
        "中军": 1,
        "王母": 1,
        "邓夫人": 1,
        "孙汝权": 1
      },
      "links": [
        {
          "source": "邓夫人",
          "target": "邓杰侯",
          "value": 2
        },
        {
          "source": "邓杰侯",
          "target": "钱玉莲",
          "value": 1
        },
        {
          "source": "邓杰侯",
          "target": "院子",
          "value": 2
        },
        {
          "source": "中军",
          "target": "邓杰侯",
          "value": 1
        },
        {
          "source": "王十朋",
          "target": "邓杰侯",
          "value": 2
        },
        {
          "source": "邓夫人",
          "target": "钱玉莲",
          "value": 1
        },
        {
          "source": "邓夫人",
          "target": "院子",
          "value": 3
        },
        {
          "source": "中军",
          "target": "邓夫人",
          "value": 1
        },
        {
          "source": "王十朋",
          "target": "邓夫人",
          "value": 3
        },
        {
          "source": "钱玉莲",
          "target": "院子",
          "value": 1
        },
        {
          "source": "中军",
          "target": "钱玉莲",
          "value": 1
        },
        {
          "source": "王十朋",
          "target": "钱玉莲",
          "value": 1
        },
        {
          "source": "中军",
          "target": "院子",
          "value": 1
        },
        {
          "source": "王十朋",
          "target": "院子",
          "value": 3
        },
        {
          "source": "中军",
          "target": "王十朋",
          "value": 1
        },
        {
          "source": "王十朋",
          "target": "王母",
          "value": 1
        },
        {
          "source": "旗牌",
          "target": "王十朋",
          "value": 1
        },
        {
          "source": "孙汝权",
          "target": "王十朋",
          "value": 1
        },
        {
          "source": "旗牌",
          "target": "王母",
          "value": 1
        },
        {
          "source": "王母",
          "target": "院子",
          "value": 1
        },
        {
          "source": "王母",
          "target": "邓夫人",
          "value": 1
        },
        {
          "source": "孙汝权",
          "target": "王母",
          "value": 1
        },
        {
          "source": "旗牌",
          "target": "院子",
          "value": 1
        },
        {
          "source": "旗牌",
          "target": "邓夫人",
          "value": 1
        },
        {
          "source": "孙汝权",
          "target": "旗牌",
          "value": 1
        },
        {
          "source": "孙汝权",
          "target": "院子",
          "value": 1
        },
        {
          "source": "孙汝权",
          "target": "邓夫人",
          "value": 1
        }
      ]
    },
    {
      "chapter": "第7章",
      "numScenes": 3,
      "numLines": 120,
      "summary": "第十九场；第二十场；第二十一场",
      "conflict": 0.603,
      "importance": 1.0,
      "locations": {
        "温州城内双门巷": 3
      },
      "characters": {
        "傧相": 1,
        "王十朋": 1,
        "邓杰侯": 1,
        "院子": 1,
        "丫鬟甲": 1,
        "钱玉莲": 1,
        "家院": 1,
        "丫鬟": 1,
        "王母": 1,
        "邓夫人": 1
      },
      "links": [
        {
          "source": "王十朋",
          "target": "王母",
          "value": 3
        },
        {
          "source": "王母",
          "target": "院子",
          "value": 2
        },
        {
          "source": "家院",
          "target": "王母",
          "value": 1
        },
        {
          "source": "王十朋",
          "target": "院子",
          "value": 2
        },
        {
          "source": "家院",
          "target": "王十朋",
          "value": 1
        },
        {
          "source": "家院",
          "target": "院子",
          "value": 1
        },
        {
          "source": "邓夫人",
          "target": "邓杰侯",
          "value": 1
        },
        {
          "source": "邓杰侯",
          "target": "院子",
          "value": 1
        },
        {
          "source": "丫鬟",
          "target": "邓杰侯",
          "value": 1
        },
        {
          "source": "王母",
          "target": "邓杰侯",
          "value": 1
        },
        {
          "source": "傧相",
          "target": "邓杰侯",
          "value": 1
        },
        {
          "source": "王十朋",
          "target": "邓杰侯",
          "value": 1
        },
        {
          "source": "邓杰侯",
          "target": "钱玉莲",
          "value": 1
        },
        {
          "source": "邓夫人",
          "target": "院子",
          "value": 1
        },
        {
          "source": "丫鬟",
          "target": "邓夫人",
          "value": 1
        },
        {
          "source": "王母",
          "target": "邓夫人",
          "value": 1
        },
        {
          "source": "傧相",
          "target": "邓夫人",
          "value": 1
        },
        {
          "source": "王十朋",
          "target": "邓夫人",
          "value": 1
        },
        {
          "source": "邓夫人",
          "target": "钱玉莲",
          "value": 1
        },
        {
          "source": "丫鬟",
          "target": "院子",
          "value": 1
        },
        {
          "source": "傧相",
          "target": "院子",
          "value": 1
        },
        {
          "source": "钱玉莲",
          "target": "院子",
          "value": 1
        },
        {
          "source": "丫鬟",
          "target": "王母",
          "value": 1
        },
        {
          "source": "丫鬟",
          "target": "傧相",
          "value": 1
        },
        {
          "source": "丫鬟",
          "target": "王十朋",
          "value": 1
        },
        {
          "source": "丫鬟",
          "target": "钱玉莲",
          "value": 1
        },
        {
          "source": "傧相",
          "target": "王母",
          "value": 1
        },
        {
          "source": "王母",
          "target": "钱玉莲",
          "value": 2
        },
        {
          "source": "傧相",
          "target": "王十朋",
          "value": 1
        },
        {
          "source": "傧相",
          "target": "钱玉莲",
          "value": 1
        },
        {
          "source": "王十朋",
          "target": "钱玉莲",
          "value": 2
        },
        {
          "source": "丫鬟甲",
          "target": "王十朋",
          "value": 1
        },
        {
          "source": "丫鬟甲",
          "target": "钱玉莲",
          "value": 1
        },
        {
          "source": "丫鬟甲",
          "target": "王母",
          "value": 1
        }
      ]
    },
    {
      "chapter": "第8章",
      "numScenes": 0,
      "numLines": 0,
      "summary": "",
      "conflict": 0.3,
      "importance": 0.0,
      "locations": {},
      "characters": {},
      "links": []
    },
    {
      "chapter": "第9章",
      "numScenes": 0,
      "numLines": 0,
      "summary": "",
      "conflict": 0.3,
      "importance": 0.0,
      "locations": {},
      "characters": {},
      "links": []
    }
  ],
  "scenes": [
    {
      "number": 1,
      "name": "第一场",
      "location": "温州城内双门巷",
      "characters": [
        {
          "name": "孙汝权",
          "importance": 1.0,
          "importance_rank": 1,
          "emotion": "neutral",
          "quote": "家中豪富广田园，圆亮珍珠大似拳。白银积累如土块，黄金堆垛似方砖。",
          "rating": 0.0,
          "role": "丑"
        }
      ],
      "summary": "第一场：1位角色，8行",
      "firstLine": 1,
      "lastLine": 8,
      "numLines": 8,
      "chapter": "第1章",
      "ratings": {
        "importance": 0.475,
        "conflict": 1.0,
        "sentiment": 0.787
      }
    },
    {
      "number": 2,
      "name": "第二场",
      "location": "温州城内双门巷",
      "characters": [
        {
          "name": "钱载和",
          "importance": 1.0,
          "importance_rank": 1,
          "emotion": "neutral",
          "quote": "鬓发皤然，居林下，一家平安。",
          "rating": 0.0,
          "role": "老生"
        },
        {
          "name": "李成",
          "importance": 0.8,
          "importance_rank": 2,
          "emotion": "positive",
          "quote": "员外爷，什么事？",
          "rating": 1.0,
          "role": ""
        },
        {
          "name": "孙氏",
          "importance": 0.6,
          "importance_rank": 3,
          "emotion": "negative",
          "quote": "人人说我赛嫦娥，我说嫦娥不如我。",
          "rating": -1.0,
          "role": ""
        },
        {
          "name": "孙汝权",
          "importance": 0.4,
          "importance_rank": 4,
          "emotion": "neutral",
          "quote": "啊哈！",
          "rating": 0.0,
          "role": "丑"
        },
        {
          "name": "王十朋",
          "importance": 0.2,
          "importance_rank": 5,
          "emotion": "positive",
          "quote": "",
          "rating": 0.333,
          "role": "小生"
        }
      ],
      "summary": "第二场：5位角色，44行",
      "firstLine": 1,
      "lastLine": 44,
      "numLines": 44,
      "chapter": "第1章",
      "ratings": {
        "importance": 0.647,
        "conflict": 0.408,
        "sentiment": 0.442
      }
    },
    {
      "number": 3,
      "name": "第三场",
      "location": "温州城内双门巷",
      "characters": [
        {
          "name": "王母",
          "importance": 1.0,
          "importance_rank": 1,
          "emotion": "neutral",
          "quote": "不求金玉贵，唯望子孙贤。",
          "rating": 0.143,
          "role": "老旦"
        },
        {
          "name": "王十朋",
          "importance": 0.6666666666666666,
          "importance_rank": 2,
          "emotion": "neutral",
          "quote": "乐守清贫，承母训，苦读寒窗。",
          "rating": 0.143,
          "role": "小生"
        },
        {
          "name": "钱载和",
          "importance": 0.3333333333333333,
          "importance_rank": 3,
          "emotion": "positive",
          "quote": "若得良缘早成就，",
          "rating": 0.333,
          "role": "老生"
        }
      ],
      "summary": "第三场：3位角色，52行",
      "firstLine": 1,
      "lastLine": 52,
      "numLines": 52,
      "chapter": "第1章",
      "ratings": {
        "importance": 0.408,
        "conflict": 0.513,
        "sentiment": 0.176
      }
    },
    {
      "number": 4,
      "name": "第四场",
      "location": "温州城内双门巷",
      "characters": [
        {
          "name": "钱载和",
          "importance": 1.0,
          "importance_rank": 1,
          "emotion": "positive",
          "quote": "女儿亲事已定准，",
          "rating": 1.0,
          "role": "老生"
        },
        {
          "name": "孙氏",
          "importance": 0.75,
          "importance_rank": 2,
          "emotion": "positive",
          "quote": "员外回来啦，请坐！",
          "rating": 0.333,
          "role": ""
        },
        {
          "name": "王十朋",
          "importance": 0.5,
          "importance_rank": 3,
          "emotion": "neutral",
          "quote": "",
          "rating": 0.0,
          "role": "小生"
        },
        {
          "name": "孙汝权",
          "importance": 0.25,
          "importance_rank": 4,
          "emotion": "neutral",
          "quote": "",
          "rating": 0.0,
          "role": "丑"
        }
      ],
      "summary": "第四场：4位角色，33行",
      "firstLine": 1,
      "lastLine": 33,
      "numLines": 33,
      "chapter": "第2章",
      "ratings": {
        "importance": 0.567,
        "conflict": 0.494,
        "sentiment": 0.467
      }
    },
    {
      "number": 5,
      "name": "第五场",
      "location": "温州城内双门巷",
      "characters": [
        {
          "name": "钱玉莲",
          "importance": 1.0,
          "importance_rank": 1,
          "emotion": "negative",
          "quote": "绣房中早妆罢针黹勤忙，",
          "rating": -0.667,
          "role": "旦"
        },
        {
          "name": "钱载和",
          "importance": 0.8,
          "importance_rank": 2,
          "emotion": "neutral",
          "quote": "只为女儿婚姻事，",
          "rating": 0.2,
          "role": "老生"
        },
        {
          "name": "孙氏",
          "importance": 0.6,
          "importance_rank": 3,
          "emotion": "neutral",
          "quote": "去到绣房问分明。",
          "rating": 0.0,
          "role": ""
        },
        {
          "name": "李成",
          "importance": 0.4,
          "importance_rank": 4,
          "emotion": "positive",
          "quote": "有！",
          "rating": 1.0,
          "role": ""
        },
        {
          "name": "王十朋",
          "importance": 0.2,
          "importance_rank": 5,
          "emotion": "negative",
          "quote": "",
          "rating": -1.0,
          "role": "小生"
        }
      ],
      "summary": "第五场：5位角色，99行",
      "firstLine": 1,
      "lastLine": 99,
      "numLines": 99,
      "chapter": "第2章",
      "ratings": {
        "importance": 0.748,
        "conflict": 0.309,
        "sentiment": -0.057
      }
    },
    {
      "number": 6,
      "name": "第六场",
      "location": "温州城内双门巷",
      "characters": [
        {
          "name": "王母",
          "importance": 1.0,
          "importance_rank": 1,
          "emotion": "positive",
          "quote": "株守寒门学孟母，",
          "rating": 0.5,
          "role": "老旦"
        },
        {
          "name": "王十朋",
          "importance": 0.6666666666666666,
          "importance_rank": 2,
          "emotion": "positive",
          "quote": "唯愿萱堂福寿全。",
          "rating": 0.333,
          "role": "小生"
        },
        {
          "name": "李成",
          "importance": 0.3333333333333333,
          "importance_rank": 3,
          "emotion": "neutral",
          "quote": "王先生在家吗？",
          "rating": 0.0,
          "role": ""
        }
      ],
      "summary": "第六场：3位角色，24行",
      "firstLine": 1,
      "lastLine": 24,
      "numLines": 24,
      "chapter": "第2章",
      "ratings": {
        "importance": 0.357,
        "conflict": 0.678,
        "sentiment": 0.255
      }
    },
    {
      "number": 7,
      "name": "第七场",
      "location": "温州城内双门巷",
      "characters": [
        {
          "name": "钱载和",
          "importance": 1.0,
          "importance_rank": 1,
          "emotion": "positive",
          "quote": "一心惦念女儿事，但愿早报好消息。",
          "rating": 0.5,
          "role": "老生"
        },
        {
          "name": "李成",
          "importance": 0.75,
          "importance_rank": 2,
          "emotion": "negative",
          "quote": "花轿到门！",
          "rating": -1.0,
          "role": ""
        },
        {
          "name": "钱玉莲",
          "importance": 0.5,
          "importance_rank": 3,
          "emotion": "negative",
          "quote": "万般皆由命，半点不由人。",
          "rating": -1.0,
          "role": "旦"
        },
        {
          "name": "孙氏",
          "importance": 0.25,
          "importance_rank": 4,
          "emotion": "negative",
          "quote": "别弄这个啦，趁早走吧！",
          "rating": -1.0,
          "role": ""
        }
      ],
      "summary": "第七场：4位角色，33行",
      "firstLine": 1,
      "lastLine": 33,
      "numLines": 33,
      "chapter": "第3章",
      "ratings": {
        "importance": 0.434,
        "conflict": 0.58,
        "sentiment": 0.0
      }
    },
    {
      "number": 8,
      "name": "第八场",
      "location": "温州城内双门巷",
      "characters": [
        {
          "name": "孙汝权",
          "importance": 1.0,
          "importance_rank": 1,
          "emotion": "positive",
          "quote": "关关睢鸠不睢鸠，在河之洲不之洲。窈窕淑女不淑女，君子好逑不好逑。",
          "rating": 1.0,
          "role": "丑"
        },
        {
          "name": "王十朋",
          "importance": 0.5,
          "importance_rank": 2,
          "emotion": "neutral",
          "quote": "",
          "rating": 0.0,
          "role": "小生"
        }
      ],
      "summary": "第八场：2位角色，7行",
      "firstLine": 1,
      "lastLine": 7,
      "numLines": 7,
      "chapter": "第3章",
      "ratings": {
        "importance": 0.533,
        "conflict": 1.0,
        "sentiment": 0.787
      }
    },
    {
      "number": 9,
      "name": "第九场",
      "location": "温州城内双门巷",
      "characters": [
        {
          "name": "王母",
          "importance": 1.0,
          "importance_rank": 1,
          "emotion": "positive",
          "quote": "韶光荏苒暮景贫，",
          "rating": 1.0,
          "role": "老旦"
        },
        {
          "name": "钱玉莲",
          "importance": 0.6666666666666666,
          "importance_rank": 2,
          "emotion": "positive",
          "quote": "老母膝下当尽心。",
          "rating": 1.0,
          "role": "旦"
        },
        {
          "name": "王十朋",
          "importance": 0.3333333333333333,
          "importance_rank": 3,
          "emotion": "positive",
          "quote": "参见母亲！",
          "rating": 0.333,
          "role": "小生"
        }
      ],
      "summary": "第九场：3位角色，29行",
      "firstLine": 1,
      "lastLine": 29,
      "numLines": 29,
      "chapter": "第3章",
      "ratings": {
        "importance": 0.5,
        "conflict": 0.328,
        "sentiment": 0.638
      }
    },
    {
      "number": 10,
      "name": "第十场",
      "location": "温州城内双门巷",
      "characters": [
        {
          "name": "邓杰侯",
          "importance": 1.0,
          "importance_rank": 1,
          "emotion": "positive",
          "quote": "一片丹心，似水清，报主隆恩。",
          "rating": 1.0,
          "role": ""
        },
        {
          "name": "院子",
          "importance": 0.6666666666666666,
          "importance_rank": 2,
          "emotion": "neutral",
          "quote": "有请夫人出堂！",
          "rating": 0.0,
          "role": ""
        },
        {
          "name": "邓夫人",
          "importance": 0.3333333333333333,
          "importance_rank": 3,
          "emotion": "neutral",
          "quote": "身受皇恩重，夫君侍朝廊。",
          "rating": 0.0,
          "role": ""
        }
      ],
      "summary": "第十场：3位角色，16行",
      "firstLine": 1,
      "lastLine": 16,
      "numLines": 16,
      "chapter": "第4章",
      "ratings": {
        "importance": 0.209,
        "conflict": 0.571,
        "sentiment": 0.764
      }
    },
    {
      "number": 11,
      "name": "第十一场",
      "location": "温州城内双门巷",
      "characters": [
        {
          "name": "王十朋",
          "importance": 1.0,
          "importance_rank": 1,
          "emotion": "neutral",
          "quote": "十年寒窗苦用功，一举成名天下闻。桑梓久别夜多虑，朝思暮想老娘亲。",
          "rating": 0.143,
          "role": "小生"
        },
        {
          "name": "四青袍",
          "importance": 0.6666666666666666,
          "importance_rank": 2,
          "emotion": "neutral",
          "quote": "啊！",
          "rating": 0.0,
          "role": ""
        },
        {
          "name": "孙汝权",
          "importance": 0.3333333333333333,
          "importance_rank": 3,
          "emotion": "positive",
          "quote": "仁兄回来啦！",
          "rating": 0.5,
          "role": "丑"
        }
      ],
      "summary": "第十一场：3位角色，31行",
      "firstLine": 1,
      "lastLine": 31,
      "numLines": 31,
      "chapter": "第4章",
      "ratings": {
        "importance": 0.503,
        "conflict": 0.615,
        "sentiment": 0.237
      }
    },
    {
      "number": 12,
      "name": "第十二场",
      "location": "温州城内双门巷",
      "characters": [
        {
          "name": "钱载和",
          "importance": 1.0,
          "importance_rank": 1,
          "emotion": "positive",
          "quote": "晓起乌鹊高声叫，",
          "rating": 0.333,
          "role": "老生"
        },
        {
          "name": "孙氏",
          "importance": 0.8571428571428571,
          "importance_rank": 2,
          "emotion": "neutral",
          "quote": "量无好事到门庭。",
          "rating": 0.0,
          "role": ""
        },
        {
          "name": "孙汝权",
          "importance": 0.7142857142857143,
          "importance_rank": 3,
          "emotion": "neutral",
          "quote": "来到啦。",
          "rating": 0.0,
          "role": "丑"
        },
        {
          "name": "李成",
          "importance": 0.5714285714285714,
          "importance_rank": 4,
          "emotion": "positive",
          "quote": "有！",
          "rating": 1.0,
          "role": ""
        },
        {
          "name": "王母",
          "importance": 0.42857142857142855,
          "importance_rank": 5,
          "emotion": "positive",
          "quote": "啊，亲家！",
          "rating": 1.0,
          "role": "老旦"
        },
        {
          "name": "钱玉莲",
          "importance": 0.2857142857142857,
          "importance_rank": 6,
          "emotion": "positive",
          "quote": "爹爹、母亲万福！",
          "rating": 0.333,
          "role": "旦"
        },
        {
          "name": "王十朋",
          "importance": 0.14285714285714285,
          "importance_rank": 7,
          "emotion": "positive",
          "quote": "",
          "rating": 1.0,
          "role": "小生"
        }
      ],
      "summary": "第十二场：7位角色，86行",
      "firstLine": 1,
      "lastLine": 86,
      "numLines": 86,
      "chapter": "第4章",
      "ratings": {
        "importance": 0.857,
        "conflict": 0.215,
        "sentiment": 0.202
      }
    },
    {
      "number": 13,
      "name": "第十三场",
      "location": "温州城内双门巷",
      "characters": [
        {
          "name": "钱玉莲",
          "importance": 1.0,
          "importance_rank": 1,
          "emotion": "negative",
          "quote": "红颜薄命多不幸，",
          "rating": -1.0,
          "role": "旦"
        },
        {
          "name": "邓杰侯",
          "importance": 0.75,
          "importance_rank": 2,
          "emotion": "positive",
          "quote": "这一女子，何故轻生？随我到衙中一叙。",
          "rating": 1.0,
          "role": ""
        },
        {
          "name": "邓夫人",
          "importance": 0.5,
          "importance_rank": 3,
          "emotion": "positive",
          "quote": "不必拜了！",
          "rating": 1.0,
          "role": ""
        },
        {
          "name": "王十朋",
          "importance": 0.25,
          "importance_rank": 4,
          "emotion": "negative",
          "quote": "",
          "rating": -0.333,
          "role": "小生"
        }
      ],
      "summary": "第十三场：4位角色，43行",
      "firstLine": 1,
      "lastLine": 43,
      "numLines": 43,
      "chapter": "第5章",
      "ratings": {
        "importance": 0.585,
        "conflict": 0.563,
        "sentiment": 0.129
      }
    },
    {
      "number": 14,
      "name": "第十四场",
      "location": "温州城内双门巷",
      "characters": [
        {
          "name": "孙汝权",
          "importance": 1.0,
          "importance_rank": 1,
          "emotion": "neutral",
          "quote": "我，孙汝权。我姑妈今儿个叫我招亲，一切均已停当，不免前去便了。",
          "rating": 0.0,
          "role": "丑"
        },
        {
          "name": "李成",
          "importance": 0.75,
          "importance_rank": 2,
          "emotion": "neutral",
          "quote": "原来是孙公子。",
          "rating": 0.0,
          "role": ""
        },
        {
          "name": "钱载和",
          "importance": 0.5,
          "importance_rank": 3,
          "emotion": "positive",
          "quote": "只为女儿事，",
          "rating": 1.0,
          "role": "老生"
        },
        {
          "name": "孙氏",
          "importance": 0.25,
          "importance_rank": 4,
          "emotion": "negative",
          "quote": "终日挂在心。",
          "rating": -0.333,
          "role": ""
        }
      ],
      "summary": "第十四场：4位角色，30行",
      "firstLine": 1,
      "lastLine": 30,
      "numLines": 30,
      "chapter": "第5章",
      "ratings": {
        "importance": 0.428,
        "conflict": 0.308,
        "sentiment": 0.067
      }
    },
    {
      "number": 15,
      "name": "第十五场",
      "location": "温州城内双门巷",
      "characters": [
        {
          "name": "王十朋",
          "importance": 1.0,
          "importance_rank": 1,
          "emotion": "negative",
          "quote": "久别家乡，念高堂，朝思暮想。",
          "rating": -0.5,
          "role": "小生"
        },
        {
          "name": "院子",
          "importance": 0.6666666666666666,
          "importance_rank": 2,
          "emotion": "neutral",
          "quote": "有！",
          "rating": 0.0,
          "role": ""
        },
        {
          "name": "旗牌",
          "importance": 0.3333333333333333,
          "importance_rank": 3,
          "emotion": "neutral",
          "quote": "参见老爷！",
          "rating": 0.0,
          "role": ""
        }
      ],
      "summary": "第十五场：3位角色，21行",
      "firstLine": 1,
      "lastLine": 21,
      "numLines": 21,
      "chapter": "第5章",
      "ratings": {
        "importance": 0.352,
        "conflict": 0.0,
        "sentiment": 0.056
      }
    },
    {
      "number": 16,
      "name": "第十六场",
      "location": "临任到闽城",
      "characters": [
        {
          "name": "邓杰侯",
          "importance": 1.0,
          "importance_rank": 1,
          "emotion": "positive",
          "quote": "幸喜临任到闽城，",
          "rating": 1.0,
          "role": ""
        },
        {
          "name": "邓夫人",
          "importance": 0.8333333333333334,
          "importance_rank": 2,
          "emotion": "positive",
          "quote": "跋涉万里为功名。",
          "rating": 1.0,
          "role": ""
        },
        {
          "name": "钱玉莲",
          "importance": 0.6666666666666666,
          "importance_rank": 3,
          "emotion": "neutral",
          "quote": "但愿与夫早相见，",
          "rating": 0.0,
          "role": "旦"
        },
        {
          "name": "院子",
          "importance": 0.5,
          "importance_rank": 4,
          "emotion": "neutral",
          "quote": "中军来见！",
          "rating": 0.0,
          "role": ""
        },
        {
          "name": "中军",
          "importance": 0.3333333333333333,
          "importance_rank": 5,
          "emotion": "neutral",
          "quote": "参见大人！",
          "rating": 0.0,
          "role": ""
        },
        {
          "name": "王十朋",
          "importance": 0.16666666666666666,
          "importance_rank": 6,
          "emotion": "positive",
          "quote": "",
          "rating": 1.0,
          "role": "小生"
        }
      ],
      "summary": "第十六场：6位角色，28行",
      "firstLine": 1,
      "lastLine": 28,
      "numLines": 28,
      "chapter": "第6章",
      "ratings": {
        "importance": 0.618,
        "conflict": 0.312,
        "sentiment": 0.769
      }
    },
    {
      "number": 17,
      "name": "第十七场",
      "location": "温州城内双门巷",
      "characters": [
        {
          "name": "王十朋",
          "importance": 1.0,
          "importance_rank": 1,
          "emotion": "negative",
          "quote": "自到潮州多惆怅，",
          "rating": -0.333,
          "role": "小生"
        },
        {
          "name": "王母",
          "importance": 0.8333333333333334,
          "importance_rank": 2,
          "emotion": "neutral",
          "quote": "离了温州地，来此是吉安。",
          "rating": 0.0,
          "role": "老旦"
        },
        {
          "name": "旗牌",
          "importance": 0.6666666666666666,
          "importance_rank": 3,
          "emotion": "neutral",
          "quote": "启禀老爷：太夫人到。",
          "rating": 0.0,
          "role": ""
        },
        {
          "name": "院子",
          "importance": 0.5,
          "importance_rank": 4,
          "emotion": "positive",
          "quote": "安抚大人有令，驿馆会见！",
          "rating": 1.0,
          "role": ""
        },
        {
          "name": "邓夫人",
          "importance": 0.3333333333333333,
          "importance_rank": 5,
          "emotion": "neutral",
          "quote": "岂敢！小妹来得鲁莽，太夫人海涵！",
          "rating": 0.0,
          "role": ""
        },
        {
          "name": "孙汝权",
          "importance": 0.16666666666666666,
          "importance_rank": 6,
          "emotion": "neutral",
          "quote": "",
          "rating": 0.0,
          "role": "丑"
        }
      ],
      "summary": "第十七场：6位角色，70行",
      "firstLine": 1,
      "lastLine": 70,
      "numLines": 70,
      "chapter": "第6章",
      "ratings": {
        "importance": 0.695,
        "conflict": 0.125,
        "sentiment": 0.062
      }
    },
    {
      "number": 18,
      "name": "第十八场",
      "location": "温州城内双门巷",
      "characters": [
        {
          "name": "邓杰侯",
          "importance": 1.0,
          "importance_rank": 1,
          "emotion": "positive",
          "quote": "只为女儿事，吉安来投亲。",
          "rating": 1.0,
          "role": ""
        },
        {
          "name": "王十朋",
          "importance": 0.75,
          "importance_rank": 2,
          "emotion": "neutral",
          "quote": "来此已是，待我进见！",
          "rating": 0.0,
          "role": "小生"
        },
        {
          "name": "邓夫人",
          "importance": 0.5,
          "importance_rank": 3,
          "emotion": "positive",
          "quote": "啊，老爷！",
          "rating": 1.0,
          "role": ""
        },
        {
          "name": "院子",
          "importance": 0.25,
          "importance_rank": 4,
          "emotion": "neutral",
          "quote": "有。",
          "rating": 0.0,
          "role": ""
        }
      ],
      "summary": "第十八场：4位角色，47行",
      "firstLine": 1,
      "lastLine": 47,
      "numLines": 47,
      "chapter": "第6章",
      "ratings": {
        "importance": 0.459,
        "conflict": 0.517,
        "sentiment": 0.525
      }
    },
    {
      "number": 19,
      "name": "第十九场",
      "location": "温州城内双门巷",
      "characters": [
        {
          "name": "王母",
          "importance": 1.0,
          "importance_rank": 1,
          "emotion": "positive",
          "quote": "上司赐婚配，",
          "rating": 1.0,
          "role": "老旦"
        },
        {
          "name": "王十朋",
          "importance": 0.75,
          "importance_rank": 2,
          "emotion": "positive",
          "quote": "烦恼在心头。",
          "rating": 1.0,
          "role": "小生"
        },
        {
          "name": "院子",
          "importance": 0.5,
          "importance_rank": 3,
          "emotion": "positive",
          "quote": "门上哪位在？",
          "rating": 1.0,
          "role": ""
        },
        {
          "name": "家院",
          "importance": 0.25,
          "importance_rank": 4,
          "emotion": "positive",
          "quote": "何事？",
          "rating": 1.0,
          "role": ""
        }
      ],
      "summary": "第十九场：4位角色，29行",
      "firstLine": 1,
      "lastLine": 29,
      "numLines": 29,
      "chapter": "第7章",
      "ratings": {
        "importance": 0.426,
        "conflict": 0.299,
        "sentiment": 0.764
      }
    },
    {
      "number": 20,
      "name": "第二十场",
      "location": "温州城内双门巷",
      "characters": [
        {
          "name": "邓杰侯",
          "importance": 1.0,
          "importance_rank": 1,
          "emotion": "positive",
          "quote": "女儿婚事安排定，",
          "rating": 1.0,
          "role": ""
        },
        {
          "name": "邓夫人",
          "importance": 0.875,
          "importance_rank": 2,
          "emotion": "neutral",
          "quote": "鸳鸯分离又重逢。",
          "rating": 0.0,
          "role": ""
        },
        {
          "name": "院子",
          "importance": 0.75,
          "importance_rank": 3,
          "emotion": "neutral",
          "quote": "花轿到门！",
          "rating": 0.0,
          "role": ""
        },
        {
          "name": "丫鬟",
          "importance": 0.625,
          "importance_rank": 4,
          "emotion": "neutral",
          "quote": "是。",
          "rating": 0.0,
          "role": ""
        },
        {
          "name": "王母",
          "importance": 0.5,
          "importance_rank": 5,
          "emotion": "neutral",
          "quote": "搭上堂来！",
          "rating": 0.0,
          "role": "老旦"
        },
        {
          "name": "傧相",
          "importance": 0.375,
          "importance_rank": 6,
          "emotion": "positive",
          "quote": "遵命！伏以：",
          "rating": 1.0,
          "role": ""
        },
        {
          "name": "王十朋",
          "importance": 0.25,
          "importance_rank": 7,
          "emotion": "neutral",
          "quote": "",
          "rating": 0.0,
          "role": "小生"
        },
        {
          "name": "钱玉莲",
          "importance": 0.125,
          "importance_rank": 8,
          "emotion": "neutral",
          "quote": "",
          "rating": 0.0,
          "role": "旦"
        }
      ],
      "summary": "第二十场：8位角色，37行",
      "firstLine": 1,
      "lastLine": 37,
      "numLines": 37,
      "chapter": "第7章",
      "ratings": {
        "importance": 0.634,
        "conflict": 0.0,
        "sentiment": 0.365
      }
    },
    {
      "number": 21,
      "name": "第二十一场",
      "location": "温州城内双门巷",
      "characters": [
        {
          "name": "王十朋",
          "importance": 1.0,
          "importance_rank": 1,
          "emotion": "neutral",
          "quote": "哎呀且住！安抚大人这样强迫婚姻，使我无计奈何。今晚不免在洞房坐他一宵，",
          "rating": 0.091,
          "role": "小生"
        },
        {
          "name": "丫鬟甲",
          "importance": 0.75,
          "importance_rank": 2,
          "emotion": "neutral",
          "quote": "启禀姑老爷！我家小姐言道：今晚洞房要熄灯相见。",
          "rating": 0.0,
          "role": ""
        },
        {
          "name": "钱玉莲",
          "importance": 0.5,
          "importance_rank": 3,
          "emotion": "negative",
          "quote": "啊，郎君！",
          "rating": -0.333,
          "role": "旦"
        },
        {
          "name": "王母",
          "importance": 0.25,
          "importance_rank": 4,
          "emotion": "positive",
          "quote": "儿呀，你知道小姐是哪个？",
          "rating": 1.0,
          "role": "老旦"
        }
      ],
      "summary": "第二十一场：4位角色，54行",
      "firstLine": 1,
      "lastLine": 54,
      "numLines": 54,
      "chapter": "第7章",
      "ratings": {
        "importance": 0.605,
        "conflict": 0.484,
        "sentiment": 0.161
      }
    }
  ],
  "characters": [
    {
      "character": "钱玉莲",
      "short": "钱玉",
      "key": "钱玉莲",
      "quote": "钱玉莲 — 旦",
      "group": "旦",
      "color": "",
      "explanation": [
        "行当: 旦",
        "所属: 旦组"
      ]
    },
    {
      "character": "王十朋",
      "short": "王十",
      "key": "王十朋",
      "quote": "王十朋 — 小生",
      "group": "生",
      "color": "",
      "explanation": [
        "行当: 小生",
        "所属: 生组"
      ]
    },
    {
      "character": "孙汝权",
      "short": "孙汝",
      "key": "孙汝权",
      "quote": "孙汝权 — 丑",
      "group": "丑",
      "color": "",
      "explanation": [
        "行当: 丑",
        "所属: 丑组"
      ]
    },
    {
      "character": "钱载和",
      "short": "钱载",
      "key": "钱载和",
      "quote": "钱载和 — 老生",
      "group": "生",
      "color": "",
      "explanation": [
        "行当: 老生",
        "所属: 生组"
      ]
    },
    {
      "character": "王母",
      "short": "王母",
      "key": "王母",
      "quote": "王母 — 老旦",
      "group": "旦",
      "color": "",
      "explanation": [
        "行当: 老旦",
        "所属: 旦组"
      ]
    },
    {
      "character": "傧相",
      "short": "傧相",
      "key": "傧相",
      "quote": "傧相 — 未知行当",
      "group": "其他",
      "color": "",
      "explanation": [
        "行当: 未知",
        "所属: 其他组"
      ]
    },
    {
      "character": "旗牌",
      "short": "旗牌",
      "key": "旗牌",
      "quote": "旗牌 — 未知行当",
      "group": "其他",
      "color": "",
      "explanation": [
        "行当: 未知",
        "所属: 其他组"
      ]
    },
    {
      "character": "邓杰侯",
      "short": "邓杰",
      "key": "邓杰侯",
      "quote": "邓杰侯 — 未知行当",
      "group": "其他",
      "color": "",
      "explanation": [
        "行当: 未知",
        "所属: 其他组"
      ]
    },
    {
      "character": "孙氏",
      "short": "孙氏",
      "key": "孙氏",
      "quote": "孙氏 — 未知行当",
      "group": "其他",
      "color": "",
      "explanation": [
        "行当: 未知",
        "所属: 其他组"
      ]
    },
    {
      "character": "中军",
      "short": "中军",
      "key": "中军",
      "quote": "中军 — 未知行当",
      "group": "其他",
      "color": "",
      "explanation": [
        "行当: 未知",
        "所属: 其他组"
      ]
    },
    {
      "character": "院子",
      "short": "院子",
      "key": "院子",
      "quote": "院子 — 未知行当",
      "group": "其他",
      "color": "",
      "explanation": [
        "行当: 未知",
        "所属: 其他组"
      ]
    },
    {
      "character": "丫鬟",
      "short": "丫鬟",
      "key": "丫鬟",
      "quote": "丫鬟 — 未知行当",
      "group": "其他",
      "color": "",
      "explanation": [
        "行当: 未知",
        "所属: 其他组"
      ]
    },
    {
      "character": "家院",
      "short": "家院",
      "key": "家院",
      "quote": "家院 — 未知行当",
      "group": "其他",
      "color": "",
      "explanation": [
        "行当: 未知",
        "所属: 其他组"
      ]
    },
    {
      "character": "丫鬟甲",
      "short": "丫鬟",
      "key": "丫鬟甲",
      "quote": "丫鬟甲 — 未知行当",
      "group": "其他",
      "color": "",
      "explanation": [
        "行当: 未知",
        "所属: 其他组"
      ]
    },
    {
      "character": "四青袍",
      "short": "四青",
      "key": "四青袍",
      "quote": "四青袍 — 未知行当",
      "group": "其他",
      "color": "",
      "explanation": [
        "行当: 未知",
        "所属: 其他组"
      ]
    },
    {
      "character": "李成",
      "short": "李成",
      "key": "李成",
      "quote": "李成 — 未知行当",
      "group": "其他",
      "color": "",
      "explanation": [
        "行当: 未知",
        "所属: 其他组"
      ]
    },
    {
      "character": "邓夫人",
      "short": "邓夫",
      "key": "邓夫人",
      "quote": "邓夫人 — 未知行当",
      "group": "其他",
      "color": "",
      "explanation": [
        "行当: 未知",
        "所属: 其他组"
      ]
    }
  ],
  "locations": [
    {
      "name": "温州城内双门巷",
      "key": "温州城内双门巷",
      "quote": "场景发生在温州城内双门巷"
    },
    {
      "name": "念高堂",
      "key": "念高堂",
      "quote": "场景发生在念高堂"
    },
    {
      "name": "临任到闽城",
      "key": "临任到闽城",
      "quote": "场景发生在临任到闽城"
    }
  ]
}